{
  "name": "Pont Audibert vers Sud",
  "description": "",
  "idPdc": 666,
  "coordinates": [
    -1.5497189172153978,
    47.2083580489973
  ],
  "counts": [
    {
      "month": "2020-01-01",
      "count": 6882
    },
    {
      "month": "2020-02-01",
      "count": 5885
    },
    {
      "month": "2020-03-01",
      "count": 4433
    },
    {
      "month": "2020-04-01",
      "count": 2528
    },
    {
      "month": "2020-05-01",
      "count": 4219
    },
    {
      "month": "2020-06-01",
      "count": 4913
    },
    {
      "month": "2020-07-01",
      "count": 4529
    },
    {
      "month": "2020-08-01",
      "count": 3407
    },
    {
      "month": "2020-09-01",
      "count": 6603
    },
    {
      "month": "2020-10-01",
      "count": 4868
    },
    {
      "month": "2020-11-01",
      "count": 3807
    },
    {
      "month": "2020-12-01",
      "count": 3317
    },
    {
      "month": "2021-01-01",
      "count": 3540
    },
    {
      "month": "2021-02-01",
      "count": 3812
    },
    {
      "month": "2021-03-01",
      "count": 4665
    },
    {
      "month": "2021-04-01",
      "count": 4651
    },
    {
      "month": "2021-05-01",
      "count": 4379
    },
    {
      "month": "2021-06-01",
      "count": 5571
    },
    {
      "month": "2021-07-01",
      "count": 4999
    },
    {
      "month": "2021-08-01",
      "count": 4954
    },
    {
      "month": "2021-09-01",
      "count": 6496
    },
    {
      "month": "2021-10-01",
      "count": 6617
    },
    {
      "month": "2021-11-01",
      "count": 6286
    },
    {
      "month": "2021-12-01",
      "count": 4355
    },
    {
      "month": "2022-01-01",
      "count": 4416
    },
    {
      "month": "2022-02-01",
      "count": 4309
    },
    {
      "month": "2022-03-01",
      "count": 5758
    },
    {
      "month": "2022-04-01",
      "count": 5573
    },
    {
      "month": "2022-05-01",
      "count": 6862
    },
    {
      "month": "2022-06-01",
      "count": 6431
    },
    {
      "month": "2022-07-01",
      "count": 5530
    },
    {
      "month": "2022-08-01",
      "count": 5507
    },
    {
      "month": "2022-09-01",
      "count": 6821
    },
    {
      "month": "2022-10-01",
      "count": 6129
    },
    {
      "month": "2022-11-01",
      "count": 5023
    },
    {
      "month": "2022-12-01",
      "count": 3951
    },
    {
      "month": "2023-01-01",
      "count": 4985
    },
    {
      "month": "2023-02-01",
      "count": 4752
    },
    {
      "month": "2023-03-01",
      "count": 6046
    },
    {
      "month": "2023-04-01",
      "count": 5506
    },
    {
      "month": "2023-05-01",
      "count": 6419
    },
    {
      "month": "2023-06-01",
      "count": 9105
    },
    {
      "month": "2023-07-01",
      "count": 7189
    },
    {
      "month": "2023-08-01",
      "count": 6523
    },
    {
      "month": "2023-09-01",
      "count": 8728
    },
    {
      "month": "2023-10-01",
      "count": 6892
    },
    {
      "month": "2023-11-01",
      "count": 5465
    },
    {
      "month": "2023-12-01",
      "count": 4695
    },
    {
      "month": "2024-01-01",
      "count": 5139
    },
    {
      "month": "2024-02-01",
      "count": 5043
    },
    {
      "month": "2024-03-01",
      "count": 5465
    },
    {
      "month": "2024-04-01",
      "count": 6085
    },
    {
      "month": "2024-05-01",
      "count": 5487
    },
    {
      "month": "2024-06-01",
      "count": 6405
    },
    {
      "month": "2024-07-01",
      "count": 6132
    },
    {
      "month": "2024-08-01",
      "count": 5054
    },
    {
      "month": "2024-09-01",
      "count": 6648
    },
    {
      "month": "2024-10-01",
      "count": 6355
    },
    {
      "month": "2024-11-01",
      "count": 5563
    },
    {
      "month": "2024-12-01",
      "count": 4783
    },
    {
      "month": "2025-01-01",
      "count": 4821
    },
    {
      "month": "2025-02-01",
      "count": 4439
    },
    {
      "month": "2025-03-01",
      "count": 5781
    },
    {
      "month": "2025-04-01",
      "count": 5813
    },
    {
      "month": "2025-05-01",
      "count": 6264
    },
    {
      "month": "2025-06-01",
      "count": 6204
    }
  ]
}