{
  "name": "Philippot vers Est",
  "description": "",
  "idPdc": 742,
  "coordinates": [
    -1.5563430663233755,
    47.21165736518504
  ],
  "counts": [
    {
      "month": "2020-01-01",
      "count": 21971
    },
    {
      "month": "2020-02-01",
      "count": 23225
    },
    {
      "month": "2020-03-01",
      "count": 14477
    },
    {
      "month": "2020-04-01",
      "count": 4290
    },
    {
      "month": "2020-05-01",
      "count": 15267
    },
    {
      "month": "2020-06-01",
      "count": 23811
    },
    {
      "month": "2020-07-01",
      "count": 28953
    },
    {
      "month": "2020-08-01",
      "count": 24471
    },
    {
      "month": "2020-09-01",
      "count": 38217
    },
    {
      "month": "2020-10-01",
      "count": 32051
    },
    {
      "month": "2020-11-01",
      "count": 21692
    },
    {
      "month": "2020-12-01",
      "count": 23485
    },
    {
      "month": "2021-01-01",
      "count": 15497
    },
    {
      "month": "2021-02-01",
      "count": 18182
    },
    {
      "month": "2021-03-01",
      "count": 24512
    },
    {
      "month": "2021-04-01",
      "count": 22579
    },
    {
      "month": "2021-05-01",
      "count": 23245
    },
    {
      "month": "2021-06-01",
      "count": 33525
    },
    {
      "month": "2021-07-01",
      "count": 33700
    },
    {
      "month": "2021-08-01",
      "count": 28903
    },
    {
      "month": "2021-09-01",
      "count": 43690
    },
    {
      "month": "2021-10-01",
      "count": 40920
    },
    {
      "month": "2021-11-01",
      "count": 35488
    },
    {
      "month": "2021-12-01",
      "count": 30197
    },
    {
      "month": "2022-01-01",
      "count": 28708
    },
    {
      "month": "2022-02-01",
      "count": 27210
    },
    {
      "month": "2022-03-01",
      "count": 37856
    },
    {
      "month": "2022-04-01",
      "count": 35034
    },
    {
      "month": "2022-05-01",
      "count": 43445
    },
    {
      "month": "2022-06-01",
      "count": 41375
    },
    {
      "month": "2022-07-01",
      "count": 35073
    },
    {
      "month": "2022-08-01",
      "count": 28950
    },
    {
      "month": "2022-09-01",
      "count": 43271
    },
    {
      "month": "2022-10-01",
      "count": 41990
    },
    {
      "month": "2022-11-01",
      "count": 36871
    },
    {
      "month": "2022-12-01",
      "count": 30078
    },
    {
      "month": "2023-01-01",
      "count": 33313
    },
    {
      "month": "2023-02-01",
      "count": 32984
    },
    {
      "month": "2023-03-01",
      "count": 36347
    },
    {
      "month": "2023-04-01",
      "count": 35114
    },
    {
      "month": "2023-05-01",
      "count": 39138
    },
    {
      "month": "2023-06-01",
      "count": 46302
    },
    {
      "month": "2023-07-01",
      "count": 34482
    },
    {
      "month": "2023-08-01",
      "count": 27124
    },
    {
      "month": "2023-09-01",
      "count": 41542
    },
    {
      "month": "2023-10-01",
      "count": 39630
    },
    {
      "month": "2023-11-01",
      "count": 37094
    },
    {
      "month": "2023-12-01",
      "count": 31832
    },
    {
      "month": "2024-01-01",
      "count": 33643
    },
    {
      "month": "2024-02-01",
      "count": 25369
    },
    {
      "month": "2024-03-01",
      "count": 34067
    },
    {
      "month": "2024-04-01",
      "count": 37420
    },
    {
      "month": "2024-05-01",
      "count": 35721
    },
    {
      "month": "2024-06-01",
      "count": 42207
    },
    {
      "month": "2024-07-01",
      "count": 38266
    },
    {
      "month": "2024-08-01",
      "count": 29317
    },
    {
      "month": "2024-09-01",
      "count": 43001
    },
    {
      "month": "2024-10-01",
      "count": 40890
    },
    {
      "month": "2024-11-01",
      "count": 2154
    },
    {
      "month": "2024-12-01",
      "count": 34037
    },
    {
      "month": "2025-01-01",
      "count": 32962
    },
    {
      "month": "2025-02-01",
      "count": 31929
    },
    {
      "month": "2025-03-01",
      "count": 41998
    },
    {
      "month": "2025-04-01",
      "count": 39880
    },
    {
      "month": "2025-05-01",
      "count": 41027
    },
    {
      "month": "2025-06-01",
      "count": 42118
    }
  ]
}